<?xml version="1.0" encoding="UTF-8"?>
<index>
	<title>Source of MineSweeper</title>
	<nodes>
		<node label="lib">
			<node label="AeonDesktopTheme.swc" url="source/lib/AeonDesktopTheme.swc"/>
			<node label="feathers.swc" url="source/lib/feathers.swc"/>
			<node label="starling.swc" url="source/lib/starling.swc"/>
		</node>
		<node label="src">
			<node icon="packageIcon" label="constants" expanded="true">
				<node icon="actionScriptIcon" label="StateConstants.as" url="source/constants/StateConstants.as.html"/>
				<node icon="actionScriptIcon" label="TextureConstants.as" url="source/constants/TextureConstants.as.html"/>
			</node>
			<node icon="packageIcon" label="controllers" expanded="true">
				<node icon="actionScriptIcon" label="MineSweeperController.as" url="source/controllers/MineSweeperController.as.html"/>
				<node icon="actionScriptIcon" label="UserInterfaceController.as" url="source/controllers/UserInterfaceController.as.html"/>
				<node icon="actionScriptIcon" label="ZoneController.as" url="source/controllers/ZoneController.as.html"/>
			</node>
			<node icon="packageIcon" label="models" expanded="true">
				<node icon="actionScriptIcon" label="MineSweeperModel.as" url="source/models/MineSweeperModel.as.html"/>
				<node icon="actionScriptIcon" label="TextureModel.as" url="source/models/TextureModel.as.html"/>
				<node icon="actionScriptIcon" label="UserInterfaceModel.as" url="source/models/UserInterfaceModel.as.html"/>
				<node icon="actionScriptIcon" label="ZoneModel.as" url="source/models/ZoneModel.as.html"/>
			</node>
			<node icon="packageIcon" label="views" expanded="true">
				<node icon="actionScriptIcon" label="MineSweeperView.as" url="source/views/MineSweeperView.as.html"/>
				<node icon="actionScriptIcon" label="UserInterfaceView.as" url="source/views/UserInterfaceView.as.html"/>
				<node icon="actionScriptIcon" label="ZoneView.as" url="source/views/ZoneView.as.html"/>
			</node>
			<node icon="mxmlAppIcon" selected="true" label="Main.as" url="source/Main.as.html"/>
			<node icon="actionScriptIcon" label="MineSweeper.as" url="source/MineSweeper.as.html"/>
		</node>
		<node label="README.md" url="source/README.md"/>
	</nodes>
	<zipfile label="Download source (ZIP, 678K)" url="MineSweeper.zip">
	</zipfile>
	<sdklink label="Download Flex SDK" url="http://www.adobe.com/go/flex451_sdk_download">
	</sdklink>
</index>
